{
  "id": "shex-commencement-deferred-0017",
  "archetype": "shex-commencement-deferred",
  "seed": 1897350478,
  "description": "NOR late Saturday under SHEX: nominal commencement falls on Sunday and must be deferred off the excepted day.",
  "claim": {
    "vessel": "SILVER GULL",
    "voyageRef": "V26-447",
    "port": "Gibraltar",
    "cargo": "Iron ore fines",
    "portTimezone": "Europe/Gibraltar"
  },
  "cpTerms": {
    "laytime_allowed_hours": 44,
    "load_rate": 9000,
    "discharge_rate": 8000,
    "turn_time_hours": 6,
    "nor_variant": "WIBON",
    "days_basis": "SHEX",
    "demurrage_rate": 34500,
    "despatch_rate": 17250,
    "currency": "EUR",
    "port_timezone": "Europe/Gibraltar"
  },
  "events": [
    {
      "id": "e1",
      "occurred_at": "2025-10-25T17:00:00.000Z",
      "event_type": "NOR_TENDERED",
      "verbatim": "NOR tendered by Master"
    },
    {
      "id": "e2",
      "occurred_at": "2025-10-25T23:00:00.000Z",
      "event_type": "ALL_FAST",
      "verbatim": "All fast"
    },
    {
      "id": "e3",
      "occurred_at": "2025-10-26T02:00:00.000Z",
      "event_type": "COMMENCED_LOADING",
      "verbatim": "Commenced loading"
    },
    {
      "id": "e4",
      "occurred_at": "2025-10-27T20:00:00.000Z",
      "event_type": "COMPLETED_LOADING",
      "verbatim": "Completed loading"
    }
  ],
  "expected": {
    "result": {
      "breakdown": [
        {
          "start_time": "2025-10-26T23:00:00.000Z",
          "end_time": "2025-10-27T20:00:00.000Z",
          "duration_hours": 21,
          "status": "laytime",
          "counts": true,
          "clause_ref": "GENCON94-6",
          "reasoning": "Laytime counting."
        }
      ],
      "totals": {
        "allowed_hours": 44,
        "used_hours": 21,
        "time_on_demurrage_hours": 0,
        "time_saved_hours": 23,
        "demurrage_amount": 0,
        "despatch_amount": 16531.25,
        "currency": "EUR"
      }
    }
  }
}
