{
  "id": "weather-open-interval-0014",
  "archetype": "weather-open-interval",
  "seed": 3884808278,
  "description": "Weather delay with no logged end: excluded all the way to completion, never cut short by unrelated events.",
  "claim": {
    "vessel": "CRIMSON TIDE",
    "voyageRef": "V24-593",
    "port": "Newcastle",
    "cargo": "Bauxite",
    "portTimezone": "Australia/Sydney"
  },
  "cpTerms": {
    "laytime_allowed_hours": 44,
    "load_rate": 10000,
    "discharge_rate": 9000,
    "turn_time_hours": 0,
    "nor_variant": "WIBON",
    "days_basis": "WWDSHEX-EIU",
    "demurrage_rate": 31000,
    "despatch_rate": 15500,
    "currency": "USD",
    "port_timezone": "Australia/Sydney"
  },
  "events": [
    {
      "id": "e1",
      "occurred_at": "2024-04-07T22:00:00.000Z",
      "event_type": "NOR_TENDERED",
      "verbatim": "NOR tendered by Master"
    },
    {
      "id": "e2",
      "occurred_at": "2024-04-08T02:00:00.000Z",
      "event_type": "ALL_FAST",
      "verbatim": "All fast"
    },
    {
      "id": "e3",
      "occurred_at": "2024-04-08T03:00:00.000Z",
      "event_type": "COMMENCED_DISCHARGE",
      "verbatim": "Commenced discharge"
    },
    {
      "id": "e4",
      "occurred_at": "2024-04-08T09:00:00.000Z",
      "event_type": "WEATHER_DELAY",
      "verbatim": "Rain — all work stopped"
    },
    {
      "id": "e5",
      "occurred_at": "2024-04-08T20:00:00.000Z",
      "event_type": "COMPLETED_DISCHARGE",
      "verbatim": "Completed discharge"
    }
  ],
  "expected": {
    "result": {
      "breakdown": [
        {
          "start_time": "2024-04-07T22:00:00.000Z",
          "end_time": "2024-04-08T09:00:00.000Z",
          "duration_hours": 11,
          "status": "laytime",
          "counts": true,
          "clause_ref": "GENCON94-6",
          "reasoning": "Laytime counting."
        },
        {
          "start_time": "2024-04-08T09:00:00.000Z",
          "end_time": "2024-04-08T20:00:00.000Z",
          "duration_hours": 11,
          "status": "weather_delay",
          "counts": false,
          "clause_ref": "GENCON94-6c",
          "reasoning": "Weather working day excluded — weather delays excluded from laytime."
        }
      ],
      "totals": {
        "allowed_hours": 44,
        "used_hours": 11,
        "time_on_demurrage_hours": 0,
        "time_saved_hours": 33,
        "demurrage_amount": 0,
        "despatch_amount": 21312.5,
        "currency": "USD"
      }
    }
  }
}
